utils_flask_sqla_geo/__init__.py
utils_flask_sqla_geo/export.py
utils_flask_sqla_geo/generic.py
utils_flask_sqla_geo/mixins.py
utils_flask_sqla_geo/schema.py
utils_flask_sqla_geo/serializers.py
utils_flask_sqla_geo/utils.py
utils_flask_sqla_geo/utilsgeometry.py
utils_flask_sqlalchemy_geo-0.3.3.dist-info/licenses/LICENSE
utils_flask_sqlalchemy_geo-0.3.3.dist-info/METADATA
utils_flask_sqlalchemy_geo-0.3.3.dist-info/WHEEL
utils_flask_sqlalchemy_geo-0.3.3.dist-info/top_level.txt
utils_flask_sqlalchemy_geo-0.3.3.dist-info/RECORD
