Metadata-Version: 2.4
Name: utils-flask-sqlalchemy-geo
Version: 0.3.3
Summary: Python lib of tools for Flask and SQLAlchemy (extension geometry)
Home-page: https://github.com/PnX-SI/Utils-Flask-SQLAlchemy-Geo
Maintainer: Parcs nationaux des Écrins et des Cévennes
Maintainer-email: geonature@ecrins-parcnational.fr
Classifier: Development Status :: 1 - Planning
Classifier: Intended Audience :: Developers
Classifier: Natural Language :: English
Classifier: Programming Language :: Python :: 3
Classifier: License :: OSI Approved :: GNU Affero General Public License v3
Classifier: Operating System :: OS Independent
License-File: LICENSE
Requires-Dist: sqlalchemy<2
Requires-Dist: fiona>=1.8.13.post1
Requires-Dist: geoalchemy2>=0.4.0
Requires-Dist: shapely>=1.8.5.post1
Requires-Dist: utils-flask-sqlalchemy>=0.4.2
Requires-Dist: marshmallow_sqlalchemy
Requires-Dist: marshmallow_geojson
Requires-Dist: geojson
Provides-Extra: tests
Requires-Dist: pytest; extra == "tests"
Requires-Dist: flask-sqlalchemy; extra == "tests"
Dynamic: classifier
Dynamic: description
Dynamic: description-content-type
Dynamic: home-page
Dynamic: license-file
Dynamic: maintainer
Dynamic: maintainer-email
Dynamic: provides-extra
Dynamic: requires-dist
Dynamic: summary
